pydeogram/__init__.py
pydeogram/__main__.py
pydeogram/api.py
pydeogram/cli.py
pydeogram/constants.py
pydeogram/jupyter_api.py
pydeogram/py.typed
pydeogram/utils.py
pydeogram/version.py
pydeogram/templates/ideogram_jupyter.js
pydeogram/templates/ideogram_template.html
pydeogram-0.0.2.dist-info/LICENSE
pydeogram-0.0.2.dist-info/METADATA
pydeogram-0.0.2.dist-info/WHEEL
pydeogram-0.0.2.dist-info/entry_points.txt
pydeogram-0.0.2.dist-info/top_level.txt
pydeogram-0.0.2.dist-info/RECORD
